Data_FolderSplit/Data_FolderSplit.py
Data_FolderSplit/__init__.py
Data_FolderSplit-1.3.dist-info/LICENSE
Data_FolderSplit-1.3.dist-info/METADATA
Data_FolderSplit-1.3.dist-info/WHEEL
Data_FolderSplit-1.3.dist-info/top_level.txt
Data_FolderSplit-1.3.dist-info/RECORD
