Metadata-Version: 2.1
Name: Data-FolderSplit
Version: 1.3
Summary: Returns folder and sub folders from the data table in csv. Basically a decision tree with folders.
Home-page: https://www.linkedin.com/in/abhishek-venkatachalam-62121049/
Author: Abhishek Venkatachalam
Author-email: abhishek.venkatachalam06@gmail.com
License: UNKNOWN
Platform: UNKNOWN
Classifier: Programming Language :: Python :: 3
Classifier: License :: OSI Approved :: GNU General Public License v3 or later (GPLv3+)
Classifier: Operating System :: OS Independent
Requires-Python: >=3.7
License-File: LICENSE
